LICENSE
README.md
pyproject.toml
bin/README.md
bin/aa-compare.py
bin/aa-info.py
bin/aa-to-dna.py
bin/aa-to-properties.py
bin/adaptor-distances.py
bin/alignment-panel-civ.py
bin/alignments-per-read.py
bin/bit-score-to-e-value.py
bin/cat-json-blast-records.py
bin/check-fasta-json-blast-consistency.py
bin/codon-distance.py
bin/combine-sequences.py
bin/compare-aa-sequences.py
bin/compare-consensuses.py
bin/compare-sequences.py
bin/convert-blast-xml-to-json.py
bin/convert-diamond-to-json.py
bin/convert-diamond-to-sam.py
bin/convert-sam-to-fastq.sh
bin/create-newick-relabeling-output.py
bin/curate-tree-ete.py
bin/curate-trees.py
bin/dark-matter-version.py
bin/describe-protein-database.py
bin/dna-to-aa.py
bin/download-genbank.sh
bin/download-refseq-viral-fasta.sh
bin/download-refseq-viral-gbff.sh
bin/e-value-to-bit-score.py
bin/extract-ORFs.py
bin/extract-reference-from-fasta-and-bam.py
bin/extract-reference-from-fasta-and-bam.py~
bin/fasta-base-indices.py
bin/fasta-count-chars.py
bin/fasta-count.py
bin/fasta-coverage.py
bin/fasta-diff.sh
bin/fasta-find.py
bin/fasta-identity-table.py
bin/fasta-ids.py
bin/fasta-join.py
bin/fasta-lengths.py
bin/fasta-match-offsets.py
bin/fasta-sequences.py
bin/fasta-sort.py
bin/fasta-split-by-id.py
bin/fasta-split-by-length.py
bin/fasta-split.py
bin/fasta-subset.py
bin/fasta-subtraction.py
bin/fasta-to-phylip.py
bin/fasta-translate.py
bin/fasta-variable-sites.py
bin/fastq-set-quality.py
bin/filter-fasta-by-complexity.py
bin/filter-fasta-by-taxonomy.py
bin/filter-fasta.py
bin/filter-hits-to-fasta.py
bin/filter-reads-alignments.py
bin/filter-sam.py
bin/format-fasta.py
bin/genbank-grep.py
bin/genome-protein-summary.py
bin/get-features.py
bin/get-hosts.py
bin/get-reads.py
bin/get-taxonomy.py
bin/graph-evalues.py
bin/ids.py
bin/local-align.py
bin/make-consensus.py
bin/make-fasta-database.py
bin/make-protein-database.py
bin/msa-find-and-extract.py
bin/ncbi-fetch-id.py
bin/newick-to-ascii.py
bin/noninteractive-alignment-panel.py
src/dark_matter.egg-info/PKG-INFO
src/dark_matter.egg-info/SOURCES.txt
src/dark_matter.egg-info/dependency_links.txt
src/dark_matter.egg-info/requires.txt
src/dark_matter.egg-info/top_level.txt
