Metadata-Version: 2.4
Name: dark-matter
Version: 7.1.1
Summary: Python library and utility scripts for working with genetic sequence data.
Author: Barbara Mühlemann, Tali Veith, Sophie Mathias, Udo Gieraths, Nikolai Zaki, David Pattinson
Author-email: Terry Jones <tcj25@cam.ac.uk>
License-Expression: MIT
Project-URL: Homepage, https://github.com/acorg/dark-matter
Project-URL: Bug Tracker, https://github.com/acorg/dark-matter/issues
Classifier: Programming Language :: Python :: 3
Classifier: Programming Language :: Python :: 3.10
Classifier: Programming Language :: Python :: 3.11
Classifier: Programming Language :: Python :: 3.12
Classifier: Programming Language :: Python :: 3.13
Classifier: Operating System :: OS Independent
Classifier: Development Status :: 4 - Beta
Classifier: Intended Audience :: Developers
Classifier: Topic :: Software Development :: Libraries :: Python Modules
Requires-Python: <3.14,>=3.10
License-File: LICENSE
Requires-Dist: biopython>=1.83
Requires-Dist: bz2file>=0.98
Requires-Dist: cachetools>=5.5.2
Requires-Dist: Cython>=0.29.16
Requires-Dist: dendropy>=5.0.1
Requires-Dist: edlib>=1.3.9.post1
Requires-Dist: ete4>=4.4.0
Requires-Dist: ipython>=8.12.3
Requires-Dist: matplotlib>=3.7.5
Requires-Dist: mysql-connector-python>=9.0.0
Requires-Dist: numpy>=1.14.2
Requires-Dist: progressbar>=2.5
Requires-Dist: prseq>=0.0.33
Requires-Dist: pysam>=0.23.0
Requires-Dist: pyzmq>=14.3.1
Requires-Dist: requests>=2.32.3
Requires-Dist: rich>=14.0.0
Requires-Dist: scikit-learn>=1.3.2
Requires-Dist: simplejson>=3.5.3
Requires-Dist: summarize-ranges>=0.1.1
Requires-Dist: types-cachetools>=5.5.0
Requires-Dist: types-requests>=2.32.0
Dynamic: license-file
